funcnodes_yolo/__init__.py
funcnodes_yolo-0.1.2.dist-info/LICENSE
funcnodes_yolo-0.1.2.dist-info/METADATA
funcnodes_yolo-0.1.2.dist-info/WHEEL
funcnodes_yolo-0.1.2.dist-info/entry_points.txt
funcnodes_yolo-0.1.2.dist-info/RECORD
